timer_score/__init__.py
timer_score/ts_checkpoint.py
timer_score/ts_timer.py
timer_score-0.1.3.dist-info/LICENSE.txt
timer_score-0.1.3.dist-info/METADATA
timer_score-0.1.3.dist-info/WHEEL
timer_score-0.1.3.dist-info/RECORD
