Metadata-Version: 2.1
Name: timer-score
Version: 0.1.3
Summary: Timer Score is a timing library that provides a score from 0 to 1 for performance
License: MIT
Author: Bob Benedict
Author-email: bbenedict@gmail.com
Requires-Python: >=3.10,<4.0
Classifier: License :: OSI Approved :: MIT License
Classifier: Programming Language :: Python :: 3
Classifier: Programming Language :: Python :: 3.10
Classifier: Programming Language :: Python :: 3.11
Classifier: Programming Language :: Python :: 3.12
Requires-Dist: numpy (>=1.26.4,<2.0.0)
